mailbomb/Mailbomb.py
mailbomb/__init__.py
mailbomb-0.0.1.5.dist-info/LICENSE.md
mailbomb-0.0.1.5.dist-info/METADATA
mailbomb-0.0.1.5.dist-info/WHEEL
mailbomb-0.0.1.5.dist-info/top_level.txt
mailbomb-0.0.1.5.dist-info/RECORD
