Metadata-Version: 2.1
Name: mailbomb
Version: 0.0.1.5
Summary: A python package to send corporate amounts of email quickly and easily
Home-page: https://github.com/D3PSI/mailbomb
Author: D3PSI
Author-email: d3psigames@gmail.com
License: GPLv3
Platform: UNKNOWN
Classifier: Programming Language :: Python :: 3
Classifier: License :: OSI Approved :: GNU General Public License v3 (GPLv3)
Classifier: Operating System :: OS Independent
